{
    "Monday": [
        "朝会",
        "生物",
        "英语",
        "数学",
        "英语",
        "物理",
        "物/心",
        "语文",
        "生物",
        "语文",
        "物理"
    ],
    "Tuesday": [
        "英语",
        "数学",
        "化学",
        "语文",
        "物理",
        "生物",
        "政治",
        "体锻",
        "化学",
        "英语",
        "数学"
    ],
    "Wednesday": [
        "英语",
        "数学",
        "数学",
        "物理",
        "化学",
        "语文",
        "体育",
        "班团",
        "物理",
        "数学",
        "化学"
    ],
    "Thursday": [
        "物理",
        "生物",
        "化学",
        "语文",
        "语文",
        "英语",
        "数学",
        "数学",
        "语文",
        "生物",
        "英语"
    ],
    "Friday": [
        "语文",
        "物理",
        "英语",
        "体育",
        "生物",
        "数学",
        "化学",
        "信息",
        "物理",
        "数学",
        "化学"
    ],
    "Saturday": [
        "生物",
        "数学",
        "物理",
        "语文",
        "语文",
        "英语",
        "英语",
        "数学",
        "",
        "",
        ""
    ],
    "Sunday": [
        [
            "",
            "生物",
            "化学",
            "物理",
            "语/英",
            "",
            "",
            "",
            "班主任",
            "数学",
            "化学"
        ]
    ]
}